Metadata-Version: 2.1
Name: qpubsub
Version: 0.1.0
Summary: UNKNOWN
Home-page: https://github.com/Qordobacode/library.qpubsub
Author: Qordoba
Author-email: sam.havens@qordoba.com
License: unlicensed
Platform: UNKNOWN
Requires-Python: >=3.6.4
